Metadata-Version: 2.1
Name: divprop
Version: 0.2.6
Summary: Division property cryptanalysis tools
Author-email: Aleksei Udovenko <aleksei@affine.group>
License: MIT License
Project-URL: Repository, https://github.com/hellman/divprop
Keywords: cryptanalysis,s-boxes,division property,integral cryptanalysis
Requires-Python: >=3.7
Requires-Dist: binteger>=0.8.0
Requires-Dist: coloredlogs>=15.0
Requires-Dist: tqdm>=4.58.0
Requires-Dist: subsets>=1.1.2
Requires-Dist: justlogs>=0.1.0
Requires-Dist: optisolveapi
